{"id": 92, "name": "Arenac County Independent", "domain": "arenacindependent.com", "bias": "center", "credibility": "high-credibility", "reporting": "high", "questionable": null, "url": "https://www.arenacindependent.com/sports/2025/06/08/panthers-pound-falcons-defeat-pioneers-to-win-district-36-title/", "title": "Panthers Pound Falcons Defeat Pioneers To Win District 36 Title", "content": "Home NewsBreaking News Breaking News Breaking News Sports Community Opinion ObituariesSubmit an Obituary Submit an Obituary Submit an Obituary ClassifiedsSubmit a ClassifiedJobs Submit a Classified Jobs Submit a Classified Jobs LegalsSubmit a Legal Notice Submit a Legal Notice Submit a Legal Notice Digital Issues Login Contact Us Subscribe Login Home NewsBreaking News Breaking News Breaking News Sports Community Opinion ObituariesSubmit an Obituary Submit an Obituary Submit an Obituary ClassifiedsSubmit a ClassifiedJobs Submit a Classified Jobs Submit a Classified Jobs LegalsSubmit a Legal Notice Submit a Legal Notice Submit a Legal Notice Digital Issues Subscribe Login **Panthers pound Falcons, defeat Pioneers to win District 36 title** June 8, 2025 Sports Login Sign Up Now Reliks rock Taste of Au GresJune 11, 2025 Flag Day and retiring flags in Arenac CountyJune 11, 2025 What consumers can do to support local farmersJune 10, 2025 Employers recognized for using Registered Apprenticeship Programs to train workersJune 9, 2025 Au Gres-Sims School District receives eleven grant awardsJune 9, 2025 A Piece of the Heart of StandishJune 8, 2025 Au Gres Music in the ParkJune 6, 2025 Free fishing, ORVing, state park entry: \u2018Three Free\u2019 Weekend June 7-8June 5, 2025 Housing precarity increasingly prevalent, persistently difficult to quantifyJune 1, 2025 Saginaw-Chippewa band awards 2% grantsMay 30, 2025 **Other News** June 7, 2025 June 6, 2025 June 5, 2025 About Accessibility Community Rules Contact Us Cookie Policy Privacy Policy Terms of Service Copyright \u00a9 2025 The Arenac County Independent, aCherryRoad MediaNewspaper. All rights reserved."}